ladim/__init__.py
ladim/__main__.py
ladim/config.py
ladim/forcing.py
ladim/grid.py
ladim/main.py
ladim/model.py
ladim/output.py
ladim/release.py
ladim/sample.py
ladim/solver.py
ladim/state.py
ladim/tracker.py
ladim/utilities.py
ladim/gridforce/ROMS.py
ladim/gridforce/__init__.py
ladim/gridforce/analytical.py
ladim/gridforce/zROMS.py
ladim/ibms/__init__.py
ladim/ibms/light.py
ladim/plugins/__init__.py
ladim-2.1.6.dist-info/licenses/LICENSE
postladim/__init__.py
postladim/cellcount.py
postladim/kde_plot.py
postladim/particlefile.py
postladim/variable.py
ladim-2.1.6.dist-info/METADATA
ladim-2.1.6.dist-info/WHEEL
ladim-2.1.6.dist-info/entry_points.txt
ladim-2.1.6.dist-info/top_level.txt
ladim-2.1.6.dist-info/RECORD
