Metadata-Version: 2.4
Name: ladim
Version: 2.1.6
Summary: Lagrangian Advection and Diffusion Model
Home-page: https://github.com/pnsaevik/ladim
Author: Bjørn Ådlandsvik
Author-email: bjorn@imr.no
Maintainer: Pål Næverlid Sævik
Maintainer-email: paal.naeverlid.saevik@hi.no
License: MIT
Classifier: Development Status :: 5 - Production/Stable
Classifier: Intended Audience :: Science/Research
Classifier: Topic :: Software Development :: Build Tools
Classifier: License :: OSI Approved :: MIT License
Classifier: Programming Language :: Python
Classifier: Operating System :: OS Independent
Requires-Python: >=3.7
License-File: LICENSE
Requires-Dist: netCDF4
Requires-Dist: numba
Requires-Dist: numexpr
Requires-Dist: numpy
Requires-Dist: pandas
Requires-Dist: pyarrow
Requires-Dist: pyproj
Requires-Dist: pyyaml
Requires-Dist: scipy
Requires-Dist: xarray
Dynamic: license-file
